abp_blocklist_parser/BlockListParser.py
abp_blocklist_parser/FastHash.py
abp_blocklist_parser/RegexParser.py
abp_blocklist_parser/__init__.py
abp_blocklist_parser-0.3.dist-info/LICENSE
abp_blocklist_parser-0.3.dist-info/METADATA
abp_blocklist_parser-0.3.dist-info/WHEEL
abp_blocklist_parser-0.3.dist-info/top_level.txt
abp_blocklist_parser-0.3.dist-info/RECORD
